pymodaq_plugins_cellkraft/__init__.py
pymodaq_plugins_cellkraft/utils.py
pymodaq_plugins_cellkraft/daq_move_plugins/__init__.py
pymodaq_plugins_cellkraft/daq_move_plugins/daq_move_CellkraftE1500.py
pymodaq_plugins_cellkraft/daq_viewer_plugins/__init__.py
pymodaq_plugins_cellkraft/daq_viewer_plugins/plugins_0D/__init__.py
pymodaq_plugins_cellkraft/daq_viewer_plugins/plugins_0D/daq_0Dviewer_Pressure.py
pymodaq_plugins_cellkraft/daq_viewer_plugins/plugins_0D/daq_0Dviewer_Template.py
pymodaq_plugins_cellkraft/hardware/__init__.py
pymodaq_plugins_cellkraft/hardware/tcpmodbus.py
pymodaq_plugins_cellkraft/hardware/cellkraft/Eseries.py
pymodaq_plugins_cellkraft/resources/VERSION
pymodaq_plugins_cellkraft/resources/__init__.py
pymodaq_plugins_cellkraft/resources/config_template.toml
pymodaq_plugins_cellkraft-1.0.1.dist-info/METADATA
pymodaq_plugins_cellkraft-1.0.1.dist-info/WHEEL
pymodaq_plugins_cellkraft-1.0.1.dist-info/entry_points.txt
pymodaq_plugins_cellkraft-1.0.1.dist-info/licenses/LICENSE
pymodaq_plugins_cellkraft-1.0.1.dist-info/RECORD
